hello/__init__.py
hello/main.py
hellor-0.0.1.dist-info/METADATA
hellor-0.0.1.dist-info/WHEEL
hellor-0.0.1.dist-info/entry_points.txt
hellor-0.0.1.dist-info/top_level.txt
hellor-0.0.1.dist-info/RECORD
